Sparkora/__init__.py
Sparkora/main.py
Sparkora/testsparkora.py
Sparkora-0.0.1.dist-info/LICENSE
Sparkora-0.0.1.dist-info/METADATA
Sparkora-0.0.1.dist-info/WHEEL
Sparkora-0.0.1.dist-info/top_level.txt
Sparkora-0.0.1.dist-info/RECORD
