Metadata-Version: 2.1
Name: Sparkora
Version: 0.0.1
Summary: Exploratory data analysis toolkit for Pyspark
Home-page: UNKNOWN
Author: Souvik Pratiher
Author-email: spratiher9@gmail.com
License: GPL-3.0 License
Download-URL: https://github.com/Spratiher9/Sparkora/archive/refs/tags/0.0.1.tar.gz
Keywords: exploratory data analysis,EDA,pyspark,preprocessing
Platform: UNKNOWN
Classifier: Development Status :: 5 - Production/Stable
Classifier: Intended Audience :: Developers
Classifier: License :: OSI Approved :: GNU General Public License v3 or later (GPLv3+)
Classifier: Topic :: Software Development :: Build Tools
Classifier: Programming Language :: Python :: 3.7
Classifier: Programming Language :: Python :: 3.8
Classifier: Programming Language :: Python :: 3.9
Classifier: Programming Language :: Python :: 3.10
License-File: LICENSE
Requires-Dist: pyspark (>=3.1.0)
Requires-Dist: IPython
